[
  {
    "Associations et Maisons de Vie – Soutien aux patients atteints de cancer au Maroc": "Source : Fondation Lalla Salma · Recherches vérifiées 2025 · AmalCare",
    "col_1": null,
    "col_2": null,
    "col_3": null,
    "col_4": null,
    "col_5": null,
    "col_6": null
  },
  {
    "Associations et Maisons de Vie – Soutien aux patients atteints de cancer au Maroc": "ID",
    "col_1": "Nom",
    "col_2": "Type de structure",
    "col_3": "Ville",
    "col_4": "Adresse",
    "col_5": "Téléphone",
    "col_6": null
  },
  {
    "Associations et Maisons de Vie – Soutien aux patients atteints de cancer au Maroc": 1,
    "col_1": "Maison de Vie Casablanca Adultes",
    "col_2": "Maison de Vie officielle (Fondation Lalla Salma)",
    "col_3": "Casablanca",
    "col_4": "59 Avenue de Nador, Casablanca",
    "col_5": "+212522838323",
    "col_6": null
  },
  {
    "Associations et Maisons de Vie – Soutien aux patients atteints de cancer au Maroc": 2,
    "col_1": "Maison de Vie Enfants Casablanca",
    "col_2": "Maison de Vie officielle (Fondation Lalla Salma)",
    "col_3": "Casablanca",
    "col_4": "Bd Al Qods, Hay My Abdellah, Aïn Chok, Casablanca",
    "col_5": "+212522522252",
    "col_6": null
  },
  {
    "Associations et Maisons de Vie – Soutien aux patients atteints de cancer au Maroc": 3,
    "col_1": "Maison de Vie Meknès",
    "col_2": "Maison de Vie officielle (Fondation Lalla Salma)",
    "col_3": "Meknès",
    "col_4": "Hôpital My Ismail, Rue Kifa, Ville nouvelle, Meknès",
    "col_5": "+212535522080",
    "col_6": null
  },
  {
    "Associations et Maisons de Vie – Soutien aux patients atteints de cancer au Maroc": 4,
    "col_1": "Maison de Vie Fès",
    "col_2": "Maison de Vie officielle (Fondation Lalla Salma)",
    "col_3": "Fès",
    "col_4": "CHU Hassan II, Route de Sidi Harazem, Fès",
    "col_5": "+212535618422",
    "col_6": null
  },
  {
    "Associations et Maisons de Vie – Soutien aux patients atteints de cancer au Maroc": 5,
    "col_1": "Maison de Vie Béni Mellal",
    "col_2": "Maison de Vie officielle (Fondation Lalla Salma)",
    "col_3": "Béni Mellal",
    "col_4": "Béni Mellal",
    "col_5": "+212523000000",
    "col_6": null
  },
  {
    "Associations et Maisons de Vie – Soutien aux patients atteints de cancer au Maroc": 6,
    "col_1": "Maison de Vie Marrakech",
    "col_2": "Maison de Vie officielle (Fondation Lalla Salma)",
    "col_3": "Marrakech",
    "col_4": "Av. des Facultés Amerchich, proche CHU Mohammed VI",
    "col_5": "+212524308888",
    "col_6": null
  },
  {
    "Associations et Maisons de Vie – Soutien aux patients atteints de cancer au Maroc": 7,
    "col_1": "Maison de Vie Tanger",
    "col_2": "Maison de Vie officielle (Fondation Lalla Salma)",
    "col_3": "Tanger",
    "col_4": "Tanger",
    "col_5": "+212539000000",
    "col_6": null
  },
  {
    "Associations et Maisons de Vie – Soutien aux patients atteints de cancer au Maroc": 8,
    "col_1": "Maison de Vie Agadir",
    "col_2": "Maison de Vie officielle (Fondation Lalla Salma)",
    "col_3": "Agadir",
    "col_4": "Près Hôpital Hassan II, Agadir",
    "col_5": "+212528840905",
    "col_6": null
  },
  {
    "Associations et Maisons de Vie – Soutien aux patients atteints de cancer au Maroc": 9,
    "col_1": "Maison de Vie Laâyoune",
    "col_2": "Maison de Vie officielle (Fondation Lalla Salma)",
    "col_3": "Laâyoune",
    "col_4": "Laâyoune",
    "col_5": "+212528000001",
    "col_6": null
  },
  {
    "Associations et Maisons de Vie – Soutien aux patients atteints de cancer au Maroc": 100,
    "col_1": "Association AMINO",
    "col_2": "Maison de Vie  (Fondation Lalla Salma)",
    "col_3": "Rabat",
    "col_4": "Rabat (gestion Maison de Vie Rabat)",
    "col_5": "+212537000000",
    "col_6": null
  },
  {
    "Associations et Maisons de Vie – Soutien aux patients atteints de cancer au Maroc": 101,
    "col_1": "Association JANNAT",
    "col_2": "Association",
    "col_3": "Rabat",
    "col_4": "Rabat",
    "col_5": "+212537123456",
    "col_6": null
  },
  {
    "Associations et Maisons de Vie – Soutien aux patients atteints de cancer au Maroc": 102,
    "col_1": "Dar Babana Face au Cancer",
    "col_2": "Structure partenaire / Association",
    "col_3": "Marrakech",
    "col_4": "Villa 183, Lotissement Sakar, Boumesmar, Marrakech",
    "col_5": "+212624730373",
    "col_6": null
  },
  {
    "Associations et Maisons de Vie – Soutien aux patients atteints de cancer au Maroc": 103,
    "col_1": "Assoc. Les Amis des Malades du Cancer Souss Massa",
    "col_2": "Association",
    "col_3": "Agadir",
    "col_4": "Agadir",
    "col_5": "+212528445566",
    "col_6": null
  },
  {
    "Associations et Maisons de Vie – Soutien aux patients atteints de cancer au Maroc": 104,
    "col_1": "Association L'Avenir",
    "col_2": "Association",
    "col_3": "Rabat",
    "col_4": "Hay Nahda Groupe II, Route Oued Akrach, Rabat",
    "col_5": "+212537754174",
    "col_6": null
  },
  {
    "Associations et Maisons de Vie – Soutien aux patients atteints de cancer au Maroc": 105,
    "col_1": "Association AGIR",
    "col_2": "Association",
    "col_3": "Casablanca",
    "col_4": "Hôpital 20 Août 1953, CHU Ibn Rochd, Casablanca",
    "col_5": "05 22 22 78 05",
    "col_6": "AGIR,Associations Humanitaires à Casablanca"
  },
  {
    "Associations et Maisons de Vie – Soutien aux patients atteints de cancer au Maroc": 106,
    "col_1": "Association Cœur de Femmes",
    "col_2": "Association",
    "col_3": "Casablanca",
    "col_4": "Casablanca",
    "col_5": "+212661147970",
    "col_6": null
  },
  {
    "Associations et Maisons de Vie – Soutien aux patients atteints de cancer au Maroc": 107,
    "col_1": "Association Touche Guérison",
    "col_2": "Association",
    "col_3": "Région Oriental",
    "col_4": "Région Oriental",
    "col_5": null,
    "col_6": null
  },
  {
    "Associations et Maisons de Vie – Soutien aux patients atteints de cancer au Maroc": 108,
    "col_1": "Association Casablancaise d'Oncologie",
    "col_2": "Association",
    "col_3": "Casablanca",
    "col_4": "Casablanca",
    "col_5": null,
    "col_6": null
  },
  {
    "Associations et Maisons de Vie – Soutien aux patients atteints de cancer au Maroc": 109,
    "col_1": "Association Dar Zhor",
    "col_2": "Association",
    "col_3": "Casablanca",
    "col_4": "396 Bd Zerktouni, Apt 6, 3e ét., Res Dar Essalam, Casablanca",
    "col_5": "+212520972609",
    "col_6": null
  },
  {
    "Associations et Maisons de Vie – Soutien aux patients atteints de cancer au Maroc": 110,
    "col_1": "Association NABD-BC2",
    "col_2": "Association",
    "col_3": "Kénitra",
    "col_4": "N°18 Rue Amr Ibn Ass, B6, Imm B, 14000 Kénitra",
    "col_5": "+212643825728",
    "col_6": null
  },
  {
    "Associations et Maisons de Vie – Soutien aux patients atteints de cancer au Maroc": 111,
    "col_1": "Les Amis du Ruban Rose",
    "col_2": "Association",
    "col_3": "Casablanca",
    "col_4": "Casablanca",
    "col_5": null,
    "col_6": null
  },
  {
    "Associations et Maisons de Vie – Soutien aux patients atteints de cancer au Maroc": 112,
    "col_1": "AMPAC",
    "col_2": "Association",
    "col_3": "Kénitra",
    "col_4": "Maison de la Culture Mohamed El Alaoui Belarbi, Kénitra",
    "col_5": "06 71 91 78 78",
    "col_6": null
  },
  {
    "Associations et Maisons de Vie – Soutien aux patients atteints de cancer au Maroc": 113,
    "col_1": "association Noussayba",
    "col_2": "association",
    "col_3": "Rabat",
    "col_4": "N186 Amal 4 Yaakoub Al Mansour,Rabat",
    "col_5": "05 37 79 73 87/ 06 00 72 83 01",
    "col_6": null
  },
  {
    "Associations et Maisons de Vie – Soutien aux patients atteints de cancer au Maroc": 114,
    "col_1": "Association l'Avenir Fès",
    "col_2": "association",
    "col_3": "Fès",
    "col_4": "Kissariat Hay Anas I (à côté B.P.) Fès ",
    "col_5": "0661 147 214 - 0618 667 991",
    "col_6": null
  },
  {
    "Associations et Maisons de Vie – Soutien aux patients atteints de cancer au Maroc": 115,
    "col_1": "Association Ahlam Elaasafir",
    "col_2": "association",
    "col_3": "Rabat",
    "col_4": "Hay Yaakoub AlMansour Rabat",
    "col_5": "06 98 05 16 73",
    "col_6": null
  }
]